diffpy/__init__.py
diffpy/mpdf/__init__.py
diffpy/mpdf/gitarchive.cfg
diffpy/mpdf/magstructure.py
diffpy/mpdf/magutils.py
diffpy/mpdf/mciftools.py
diffpy/mpdf/mpdf3Dcalculator.py
diffpy/mpdf/mpdfcalculator.py
diffpy/mpdf/mpdftransformer.py
diffpy/mpdf/simpleparser.py
diffpy/mpdf/version.cfg
diffpy/mpdf/version.py
diffpy/mpdf/visualize3D.py
diffpy/mpdf/tests/MnO_cubic.cif
diffpy/mpdf/tests/__init__.py
diffpy/mpdf/tests/run.py
diffpy/mpdf/tests/testbasicmpdf.py
diffpy/mpdf/tests/testdata.fgr
diffpy/mpdf/tests/testformfactor.py
diffpy/mpdf/tests/testgetdiffdata.py
diffpy/mpdf/tests/testmpdffromcif.py
diffpy/mpdf/tests/testmpdffromselfcreated.py
diffpy/mpdf/tests/testspinsatoms.py
diffpy/mpdf/tests/testdata/MnO_cubic.cif
diffpy/mpdf/tests/testdata/testdata.fgr
diffpy_mpdf-1.0.4.1.dist-info/licenses/AUTHORS.txt
diffpy_mpdf-1.0.4.1.dist-info/licenses/LICENSE.txt
diffpy_mpdf-1.0.4.1.dist-info/METADATA
diffpy_mpdf-1.0.4.1.dist-info/WHEEL
diffpy_mpdf-1.0.4.1.dist-info/top_level.txt
diffpy_mpdf-1.0.4.1.dist-info/RECORD
